private_project_windows_snake_game/__init__.py
private_project_windows_snake_game-0.1.0.dist-info/licenses/LICENSE.txt
private_project_windows_snake_game-0.1.0.dist-info/METADATA
private_project_windows_snake_game-0.1.0.dist-info/WHEEL
private_project_windows_snake_game-0.1.0.dist-info/top_level.txt
private_project_windows_snake_game-0.1.0.dist-info/RECORD
