Metadata-Version: 2.4
Name: private_project_windows_snake_game
Version: 0.1.0
Summary: A Windows snake game project.It is a private project but you can use it if you trust me.
Author: ramimK0bir
Author-email: kobirbiddut81@gmail.com
Classifier: Programming Language :: Python :: 3
Classifier: Operating System :: Microsoft :: Windows
Classifier: License :: OSI Approved :: MIT License
Requires-Python: >=3.7
License-File: LICENSE.txt
Requires-Dist: pynput
Dynamic: author
Dynamic: author-email
Dynamic: classifier
Dynamic: description
Dynamic: description-content-type
Dynamic: license-file
Dynamic: requires-dist
Dynamic: requires-python
Dynamic: summary
